README.md
setup.py
opject_server/__init__.py
opject_server/constants.py
opject_server/endpoints.py
opject_server/server.py
opject_server/utilities.py
opject_server.egg-info/PKG-INFO
opject_server.egg-info/SOURCES.txt
opject_server.egg-info/dependency_links.txt
opject_server.egg-info/top_level.txt