Metadata-Version: 2.1
Name: opject-server
Version: 0.0.0
Summary: server for object passing
Home-page: https://github.com/plurid/opject
Author: ly3xqhl8g9
Author-email: ly3xqhl8g9@plurid.com
License: UNKNOWN
Platform: UNKNOWN
Classifier: Programming Language :: Python :: 3
Classifier: License :: OSI Approved :: MIT License
Classifier: Operating System :: OS Independent
Requires-Python: >=3.6
